odoo/addons/sale_quotation_template_product_multi_add/README.rst
odoo/addons/sale_quotation_template_product_multi_add/__init__.py
odoo/addons/sale_quotation_template_product_multi_add/__manifest__.py
odoo/addons/sale_quotation_template_product_multi_add/i18n/es.po
odoo/addons/sale_quotation_template_product_multi_add/i18n/it.po
odoo/addons/sale_quotation_template_product_multi_add/i18n/sale_quotation_template_product_multi_add.pot
odoo/addons/sale_quotation_template_product_multi_add/readme/CONTRIBUTORS.rst
odoo/addons/sale_quotation_template_product_multi_add/readme/DESCRIPTION.rst
odoo/addons/sale_quotation_template_product_multi_add/readme/USAGE.rst
odoo/addons/sale_quotation_template_product_multi_add/security/ir.model.access.csv
odoo/addons/sale_quotation_template_product_multi_add/static/description/icon.png
odoo/addons/sale_quotation_template_product_multi_add/static/description/index.html
odoo/addons/sale_quotation_template_product_multi_add/tests/__init__.py
odoo/addons/sale_quotation_template_product_multi_add/tests/test_sale.py
odoo/addons/sale_quotation_template_product_multi_add/views/sale_view.xml
odoo/addons/sale_quotation_template_product_multi_add/wizards/__init__.py
odoo/addons/sale_quotation_template_product_multi_add/wizards/sale_template_add_products.py
odoo/addons/sale_quotation_template_product_multi_add/wizards/sale_template_add_products_view.xml
odoo14_addon_sale_quotation_template_product_multi_add-14.0.1.0.2.dev12.dist-info/METADATA
odoo14_addon_sale_quotation_template_product_multi_add-14.0.1.0.2.dev12.dist-info/WHEEL
odoo14_addon_sale_quotation_template_product_multi_add-14.0.1.0.2.dev12.dist-info/top_level.txt
odoo14_addon_sale_quotation_template_product_multi_add-14.0.1.0.2.dev12.dist-info/RECORD
